CHANGES.txt
LICENSE.txt
MANIFEST.in
README.txt
TODO.txt
bootstrap.py
buildout.cfg
setup.py
src/j01/__init__.py
src/j01.select2.egg-info/PKG-INFO
src/j01.select2.egg-info/SOURCES.txt
src/j01.select2.egg-info/dependency_links.txt
src/j01.select2.egg-info/namespace_packages.txt
src/j01.select2.egg-info/not-zip-safe
src/j01.select2.egg-info/requires.txt
src/j01.select2.egg-info/top_level.txt
src/j01/select2/__init__.py
src/j01/select2/configure.zcml
src/j01/select2/converter.py
src/j01/select2/interfaces.py
src/j01/select2/jsonrpc.py
src/j01/select2/jsonrpc.zcml
src/j01/select2/term.py
src/j01/select2/widget.py
src/j01/select2/widget_display.pt
src/j01/select2/widget_hidden.pt
src/j01/select2/widget_input.pt
src/j01/select2/css/j01.select2.css
src/j01/select2/img/j01Select2.png
src/j01/select2/img/j01Select2Spinner.gif
src/j01/select2/img/j01Select2x2.png
src/j01/select2/js/j01.select2.js
src/j01/select2/js/j01.select2.min.js
src/j01/select2/less/j01.select2.less
src/j01/select2/less/source/core.less
src/j01/select2/less/source/variables.less
src/j01/select2/source/select2-3.3.1.zip
src/j01/select2/source/select2-3.5.2.zip
src/j01/select2/source/select2-3.5.4.zip
src/j01/select2/source/select2-4.0.13.zip
src/j01/select2/tests/__init__.py
src/j01/select2/tests/checker.txt
src/j01/select2/tests/checker_MIGRATION_P2P3.py
src/j01/select2/tests/tests.py