Metadata-Version: 2.1
Name: j01.select2
Version: 5.0.5
Summary: Multi select2 4.0 widget based on JQuery and z3c.form for Zope 3
Home-page: https://pypi.org/project/j01.select2
Author: Roger Ineichen, Projekt01 GmbH
Author-email: dev@projekt01.ch
License: ZPL 2.1
Keywords: J01 z3c multi select select2 widget form JQuery Zope3
Platform: UNKNOWN
Classifier: Development Status :: 5 - Production/Stable
Classifier: Environment :: Web Environment
Classifier: Intended Audience :: Developers
Classifier: License :: OSI Approved :: Zope Public License
Classifier: Programming Language :: Python
Classifier: Natural Language :: English
Classifier: Operating System :: OS Independent
Classifier: Topic :: Internet :: WWW/HTTP
Classifier: Framework :: Zope3
Provides-Extra: test
